django_parlor-0.0.3.dist-info/licenses/LICENSE
parlor/__init__.py
parlor/admin.py
parlor/models.py
django_parlor-0.0.3.dist-info/METADATA
django_parlor-0.0.3.dist-info/WHEEL
django_parlor-0.0.3.dist-info/top_level.txt
django_parlor-0.0.3.dist-info/RECORD
