Metadata-Version: 2.4
Name: django-parlor
Version: 0.0.3
Summary: Django model translations with even less nasty hacks.
Author-email: Tobias Bengfort <tobias.bengfort@posteo.de>
License-Expression: MIT
Project-URL: Homepage, https://github.com/xi/django-parlor
Keywords: django,translation
Classifier: Development Status :: 4 - Beta
Classifier: Environment :: Web Environment
Classifier: Framework :: Django
Classifier: Intended Audience :: Developers
Classifier: Operating System :: OS Independent
Classifier: Programming Language :: Python
Classifier: Programming Language :: Python :: 3
License-File: LICENSE
Requires-Dist: django>=4.2
Dynamic: license-file
